adafruit_dht.py
adafruit_circuitpython_dht-4.0.2.dist-info/LICENSE
adafruit_circuitpython_dht-4.0.2.dist-info/METADATA
adafruit_circuitpython_dht-4.0.2.dist-info/WHEEL
adafruit_circuitpython_dht-4.0.2.dist-info/top_level.txt
adafruit_circuitpython_dht-4.0.2.dist-info/RECORD
