Metadata-Version: 2.1
Name: adafruit-circuitpython-dht
Version: 4.0.2
Summary: CircuitPython support for DHT11 and DHT22 type temperature/humidity devices
Author-email: Adafruit Industries <circuitpython@adafruit.com>
License: MIT
Project-URL: Homepage, https://github.com/adafruit/Adafruit_CircuitPython_DHT
Keywords: adafruit,dht,hardware,sensors,temperature,humidity,micropython,circuitpython
Classifier: Intended Audience :: Developers
Classifier: Topic :: Software Development :: Libraries
Classifier: Topic :: Software Development :: Embedded Systems
Classifier: Topic :: System :: Hardware
Classifier: License :: OSI Approved :: MIT License
Classifier: Programming Language :: Python :: 3
Provides-Extra: optional
License-File: LICENSE
